README.md
setup.py
src/vdk/plugin/data_sources/auto_generated.py
src/vdk/plugin/data_sources/config.py
src/vdk/plugin/data_sources/data_source.py
src/vdk/plugin/data_sources/factory.py
src/vdk/plugin/data_sources/hook_spec.py
src/vdk/plugin/data_sources/ingester.py
src/vdk/plugin/data_sources/plugin_entry.py
src/vdk/plugin/data_sources/sources_command.py
src/vdk/plugin/data_sources/state.py
src/vdk/plugin/data_sources/mapping/data_flow.py
src/vdk/plugin/data_sources/mapping/definitions.py
src/vdk/plugin/data_sources/mapping/toml_parser.py
src/vdk_data_sources.egg-info/PKG-INFO
src/vdk_data_sources.egg-info/SOURCES.txt
src/vdk_data_sources.egg-info/dependency_links.txt
src/vdk_data_sources.egg-info/entry_points.txt
src/vdk_data_sources.egg-info/requires.txt
src/vdk_data_sources.egg-info/top_level.txt
tests/test_autogenerated_data_source.py
tests/test_config.py
tests/test_factory.py
tests/test_ingester.py
tests/test_sources_command.py
tests/test_state.py