Metadata-Version: 2.1
Name: vdk-data-sources
Version: 0.1.1058821821
Summary: Enables Versatile Data Kit (VDK) to integrate with various data sources by providing a unified interface for data ingestion and management.
Home-page: https://github.com/vmware/versatile-data-kit
Project-URL: Documentation, https://github.com/vmware/versatile-data-kit/tree/main/projects/vdk-plugins/vdk-data-sources
Project-URL: Source Code, https://github.com/vmware/versatile-data-kit/tree/main/projects/vdk-plugins/vdk-data-sources
Project-URL: Bug Tracker, https://github.com/vmware/versatile-data-kit/issues/new/choose
Classifier: Development Status :: 2 - Pre-Alpha
Classifier: License :: OSI Approved :: Apache Software License
Classifier: Programming Language :: Python :: 3.7
Classifier: Programming Language :: Python :: 3.8
Classifier: Programming Language :: Python :: 3.9
Classifier: Programming Language :: Python :: 3.10
Classifier: Programming Language :: Python :: 3.11
Requires-Dist: vdk-core
Requires-Dist: toml
Requires-Dist: vdk-control-cli
